cnvrt/__init__.py
cnvrt/sgdConvertor.py
dwnld/__init__.py
dwnld/downloader.py
cnvrt-0.0.1.dist-info/METADATA
cnvrt-0.0.1.dist-info/WHEEL
cnvrt-0.0.1.dist-info/top_level.txt
cnvrt-0.0.1.dist-info/RECORD
