Metadata-Version: 2.1
Name: cnvrt
Version: 0.0.1
Summary: A package to convert SGD to other currencies
Author: gladloh
Author-email: gladys.loh@live.com
License: MIT
Keywords: conversion
Classifier: Development Status :: 3 - Alpha
Classifier: Intended Audience :: Developers
Classifier: License :: OSI Approved :: MIT License
Classifier: Programming Language :: Python :: 3
